camerata-0.5.0.dist-info/METADATA
camerata-0.5.0.dist-info/WHEEL
camerata-0.5.0.dist-info/license_files/LICENSE
camerata/__init__.py
camerata/camerata.cpython-39-darwin.so
camerata-0.5.0.dist-info/RECORD
